LICENSE.txt
pyproject.toml
setup.cfg
setup.py
decorationLine/__init__.py
decorationLine/decorationLine.py
decorationLine.egg-info/PKG-INFO
decorationLine.egg-info/SOURCES.txt
decorationLine.egg-info/dependency_links.txt
decorationLine.egg-info/top_level.txt